dictionary/__init__.py
dictionary/dictionary.py
onatpostaci_cs453_hw1-6.1.9.dist-info/METADATA
onatpostaci_cs453_hw1-6.1.9.dist-info/WHEEL
onatpostaci_cs453_hw1-6.1.9.dist-info/top_level.txt
onatpostaci_cs453_hw1-6.1.9.dist-info/RECORD
