Metadata-Version: 2.1
Name: onatpostaci-cs453-hw1
Version: 6.1.9
Summary: UNKNOWN
Author: Ömer Onat Postacı
License: UNKNOWN
Platform: UNKNOWN
Requires-Python: >=3.8
Requires-Dist: requests (>=2.23.0)
